README.md
setup.py
micro_blue/__init__.py
micro_blue.egg-info/PKG-INFO
micro_blue.egg-info/SOURCES.txt
micro_blue.egg-info/dependency_links.txt
micro_blue.egg-info/top_level.txt
micro_blue/gpiozero_lib/__init__.py
micro_blue/gpiozero_lib/tm1637.py
micro_blue/gpiozero_lib/traffic_light.py
micro_blue/micropython_lib/__init__.py