Metadata-Version: 2.1
Name: micro-blue
Version: 0.2.4
Summary: micro-blue is an extension for Raspberry Pi that collects a lot of sensor drivers.
Home-page: https://github.com/tim2anna/micro-blue
Author: Anna
Author-email: 
License: BSD License
Platform: all
Classifier: Environment :: Web Environment
Classifier: Intended Audience :: Developers
Classifier: License :: OSI Approved :: BSD License
Classifier: Operating System :: OS Independent
Classifier: Programming Language :: Python
Classifier: Topic :: Internet :: WWW/HTTP :: Dynamic Content
Classifier: Topic :: Software Development :: Libraries :: Python Modules
Classifier: Programming Language :: Python :: 3.7
Classifier: Programming Language :: Python :: 3.8
